<?xml version="1.0" encoding="UTF-8"?>
<song>
	<id>1</id>
	<title>Mtakatifu, Mtakatifu, Mtakatifu</title>
	<englishTitle>Holy, Holy, Holy</englishTitle>
	<verses>
		<verse>
			U Mtakatifu! Mungu Mwenyezi!
			Alfajiri sifa zako tutaimba;
			U Mtakatifu, Bwana wa huruma,
			Mungu wa vyote milele.
		</verse>
		<verse>
			U Mtakatifu! Na malaika
			Wengi sana wanakuabudu wote;
			Elfu na maelfu wanakusujudu
			Wa zamani na hata milele.
		</verse>
		<verse>
			U Mtakatifu! ingawa giza
			Lakuficha fahari tusiione,
			U Mtakatifu! Wewe peke yako,
			Kamili kwa uwezo na pendo.
		</verse>
	</verses>
</song>