<?xml version="1.0" encoding="utf-8" ?>
<song>
	<id>43</id>
	<title>Furaha Gani!</title>									
	<englishTitle>What a Fellowship</englishTitle>									
	<verses>
		<verse>
			Furaha gani na ushiriki,
			Nikimtegemea Yesu tu!
			Baraka gani, tena amani,
			Nikimtegemea Yesu tu!
		</verse>
		<refrain>
			Tegemea, salama bila hatari;
			Tegemea, tegemea Mwokozi Yesu.			
		</refrain>
		<verse>
			Nitaiweza njia nyembamba,
			Nikimtegemea Yesu tu;
			Njia 'tazidi kuwa rahisi,
			Nikimtegemea Yesu tu.
		</verse>
		<verse>
			Sina sababu ya kuogopa,
			Nikimtegemea Yesu tu;
			Atakuwa karibu daima,
			Nikimtegemea Yesu tu.
		</verse>
	</verses>
</song>